{
  "unitId": 196,
  "coreData": {
    "forms": [
      {
        "formId": 0,
        "name": "キャットマンダディ",
        "stats": [3950, 5, 12, 2500, 105, 440, 3680, 2350, 0, 320, 0, 0, 1, 70, 0, 5, 1, 0, 0, 0, 0, 1, 0, 0, 0, 0, 0, 0, 0, 0, 1, 0, 0, 0, 0, 0, 0, 0, 0, 0, 0, 0, 0, 0, 0, 0, 0, 0, 0, 0, 0, 0, 0, 0, 0, -1, 0, -1, 0, 0, 0, 0, 0, 1, 0, 0, -1, 0, 0, 0, 0, 0, 0, 0, 0, 0, 0, 0, 0, 0],
        "animLength": 161
      },
      {
        "formId": 1,
        "name": "キャットマンダーク",
        "stats": [3950, 5, 12, 2500, 105, 440, 3680, 2350, 0, 320, 0, 0, 1, 70, 0, 5, 0, 0, 0, 0, 1, 1, 0, 0, 0, 0, 0, 0, 0, 0, 1, 0, 0, 0, 0, 0, 0, 0, 0, 0, 0, 0, 0, 0, 0, 0, 0, 0, 0, 0, 0, 0, 0, 0, 0, -1, 0, -1, 0, 0, 0, 0, 0, 1, 0, 0, -1, 0, 0, 0, 0, 0, 0, 0, 0, 0, 0, 0, 0, 0],
        "animLength": 161
      },
      {
        "formId": 2,
        "name": "キャットマンライジング",
        "stats": [3950, 5, 12, 2500, 105, 440, 3680, 2350, 0, 320, 0, 0, 1, 70, 0, 5, 0, 0, 0, 0, 0, 1, 0, 0, 0, 0, 0, 0, 0, 0, 1, 0, 0, 0, 0, 0, 0, 0, 0, 0, 0, 0, 0, 0, 0, 0, 0, 0, 0, 0, 0, 0, 0, 0, 0, -1, 0, -1, 0, 0, 0, 0, 0, 1, 0, 0, -1, 0, 0, 0, 0, 0, 0, 0, 0, 0, 0, 0, 1, 1],
        "animLength": 161
      }
    ],
    "rarity": {
      "id": 4,
      "name": "超激レア",
      "maxLevels": [60, 70]
    },
    "levelRates": [20, 20, 20, 20, 20, 20, 10, 10, 5, 5, 5, 5, 5, 5, 5, 5, 5, 5, 5, 5]
  },
  "auxiliaryData": {
    "names": ["キャットマンダディ", "キャットマンダーク", "キャットマンライジング"],
    "talents": {
      "hasTalents": true,
      "hasUltra": false,
      "talentList": [
        {
          "id": 51,
          "name": "攻撃無効",
          "type": "normal",
          "data": [51, 10, 30, 30, 24, 60, 0, 0, 0, 0, 60, 7, -1, 0],
          "npCost": 235,
          "isTotal": true
        },
        {
          "id": 49,
          "name": "ワープ無効",
          "type": "normal",
          "data": [49, 0, 0, 0, 0, 0, 0, 0, 0, 0, 58, 9, -1, 0],
          "npCost": 100,
          "isTotal": false
        },
        {
          "id": 45,
          "name": "動きを止める無効",
          "type": "normal",
          "data": [45, 0, 0, 0, 0, 0, 0, 0, 0, 0, 54, 9, -1, 0],
          "npCost": 100,
          "isTotal": false
        },
        {
          "id": 32,
          "name": "基本体力アップ",
          "type": "normal",
          "data": [32, 10, 2, 20, 0, 0, 0, 0, 0, 0, 27, 8, -1, 0],
          "npCost": 175,
          "isTotal": true
        },
        {
          "id": 31,
          "name": "基本攻撃力アップ",
          "type": "normal",
          "data": [31, 10, 2, 20, 0, 0, 0, 0, 0, 0, 28, 8, -1, 0],
          "npCost": 175,
          "isTotal": true
        }
      ]
    }
  }
}

