{
  "unitId": 246,
  "sortKey": 1900040,
  "isLimited": false,
  "isSeasonal": false,
  "coreData": {
    "forms": [
      {
        "formId": 0,
        "name": "ちびウシネコ",
        "stats": [200, 5, 20, 13, 0, 130, 500, 135, 0, 320, 0, 0, 0, 6, 0, 9, 0, 0, 0, 0, 0, 0, 0, 0, 0, 0, 0, 0, 0, 0, 0, 0, 0, 0, 0, 0, 0, 0, 0, 0, 0, 0, 0, 0, 0, 0, 0, 0, 0, 0, 0, 0, 0, 0, 0],
        "animLength": 10
      },
      {
        "formId": 1,
        "name": "ちびネコキリン",
        "stats": [200, 5, 20, 13, 0, 130, 500, 135, 0, 320, 0, 0, 0, 6, 0, 9, 0, 0, 0, 0, 0, 0, 0, 0, 0, 0, 0, 0, 0, 0, 0, 0, 0, 0, 0, 0, 0, 0, 0, 0, 0, 0, 0, 0, 0, 0, 0, 0, 0, 0, 0, 0, 0, 0, 0],
        "animLength": 10
      },
      {
        "formId": 2,
        "name": "ちびネコライオン",
        "stats": [800, 5, 20, 26, 0, 130, 500, 195, 0, 320, 0, 0, 0, 6, 0, 9, 0, 0, 0, 0, 0, 0, 0, 0, 0, 0, 0, 0, 0, 0, 0, 0, 0, 0, 0, 0, 0, 0, 0, 0, 0, 0, 0, 0, 0, 0, 1, 0, 0, 0, 0, 0, 0, 0, 0],
        "animLength": 10
      }
    ],
    "rarity": {
      "id": 1,
      "name": "EX",
      "maxLevels": [50, 60]
    },
    "levelRates": [20, 20, 20, 20, 20, 20, 10, 10, 10, 10, 10, 10, 10, 10, 10, 10, 10, 10, 10, 10]
  },
  "auxiliaryData": {
    "names": ["ちびウシネコ", "ちびネコキリン", "ちびネコライオン"],
    "talents": {
      "hasTalents": true,
      "hasUltra": false,
      "talentList": [
        {
          "id": 58,
          "name": "シールドブレイカー",
          "type": "normal",
          "data": [58, 10, 1, 10, 0, 0, 0, 0, 0, 0, 78, 4, -1, 0],
          "npCost": 165,
          "isTotal": true
        },
        {
          "id": 25,
          "name": "生産コスト割引",
          "type": "normal",
          "data": [25, 10, 20, 200, 0, 0, 0, 0, 0, 0, 31, 5, -1, 0],
          "npCost": 125,
          "isTotal": true
        },
        {
          "id": 55,
          "name": "裂波ダメージ無効",
          "type": "normal",
          "data": [55, 0, 0, 0, 0, 0, 0, 0, 0, 0, 67, 6, -1, 0],
          "npCost": 75,
          "isTotal": false
        },
        {
          "id": 32,
          "name": "基本体力アップ",
          "type": "normal",
          "data": [32, 10, 2, 20, 0, 0, 0, 0, 0, 0, 27, 5, -1, 0],
          "npCost": 125,
          "isTotal": true
        },
        {
          "id": 31,
          "name": "基本攻撃力アップ",
          "type": "normal",
          "data": [31, 10, 2, 20, 0, 0, 0, 0, 0, 0, 28, 5, -1, 0],
          "npCost": 125,
          "isTotal": true
        }
      ]
    }
  }
}

