{
  "unitId": 258,
  "sortKey": 4006010,
  "coreData": {
    "forms": [
      {
        "formId": 0,
        "name": "守護神アヌビス",
        "stats": [2400, 3, 18, 2100, 76, 425, 2800, 2200, 0, 320, 0, 0, 1, 116, 0, 9, 0, 0, 0, 0, 0, 0, 0, 0, 0, 0, 0, 0, 0, 0, 0, 0, 0, 0, 0, 0, 0, 0, 0, 0, 0, 0, 0, 0, 0, 0, 1, 0, 0, 0, 1, 0, 1, 0, 0, -1, 0, -1, 0, 0, 0, 0, 0, 1, 0, 0, -1, 0, 0, 0, 0, 0, 0, 0, 0, 0, 0, 0, 0, 0, 0, 0, 0, 0, 0, 0, 0, 0, 0, 0, 0, 0, 0, 0],
        "animLength": 157
      },
      {
        "formId": 1,
        "name": "パーフェクトアヌビス",
        "stats": [3200, 3, 18, 2800, 76, 425, 2800, 2200, 0, 320, 0, 0, 1, 116, 0, 9, 0, 0, 0, 0, 0, 0, 0, 0, 0, 0, 0, 0, 0, 0, 0, 0, 0, 0, 0, 0, 0, 0, 0, 0, 0, 0, 0, 0, 0, 0, 1, 0, 0, 0, 1, 0, 1, 0, 0, -1, 0, -1, 0, 0, 0, 0, 0, 1, 0, 0, -1, 0, 0, 0, 0, 0, 0, 0, 0, 0, 0, 0, 0, 0, 0, 0, 0, 0, 0, 0, 0, 0, 0, 0, 0, 0, 0, 0],
        "animLength": 157
      },
      {
        "formId": 2,
        "name": "Ｇパーフェクトアヌビス",
        "stats": [4000, 3, 18, 3500, 76, 425, 2800, 2200, 0, 320, 0, 0, 1, 116, 0, 9, 0, 0, 0, 0, 0, 0, 0, 0, 0, 0, 0, 0, 0, 0, 0, 0, 0, 0, 0, 0, 0, 0, 0, 0, 0, 0, 0, 0, 0, 0, 1, 0, 1, 0, 1, 0, 1, 0, 0, -1, 0, -1, 0, 0, 0, 0, 0, 1, 0, 0, -1, 0, 0, 0, 0, 0, 0, 0, 0, 0, 0, 0, 0, 0, 0, 0, 0, 0, 0, 0, 0, 0, 0, 0, 0, 0, 0, 0],
        "animLength": 157
      }
    ],
    "rarity": {
      "id": 4,
      "name": "超激レア",
      "maxLevels": [60, 70]
    },
    "levelRates": [20, 20, 20, 20, 20, 20, 10, 10, 5, 5, 5, 5, 5, 5, 5, 5, 5, 5, 5, 5]
  },
  "auxiliaryData": {
    "names": ["守護神アヌビス", "パーフェクトアヌビス", "Ｇパーフェクトアヌビス"],
    "talents": {
      "hasTalents": true,
      "hasUltra": true,
      "talentList": [
        {
          "id": 56,
          "name": "裂波攻撃",
          "type": "normal",
          "data": [56, 10, 3, 30, 1, 1, 800, 800, 1000, 1000, 68, 7, -1, 0],
          "npCost": 235,
          "isTotal": true
        },
        {
          "id": 55,
          "name": "裂波ダメージ無効",
          "type": "normal",
          "data": [55, 0, 0, 0, 0, 0, 0, 0, 0, 0, 67, 9, -1, 0],
          "npCost": 100,
          "isTotal": false
        },
        {
          "id": 15,
          "name": "バリアブレイカー",
          "type": "normal",
          "data": [15, 10, 16, 70, 0, 0, 0, 0, 0, 0, 15, 7, -1, 0],
          "npCost": 235,
          "isTotal": true
        },
        {
          "id": 32,
          "name": "基本体力アップ",
          "type": "normal",
          "data": [32, 10, 2, 20, 0, 0, 0, 0, 0, 0, 27, 8, -1, 0],
          "npCost": 175,
          "isTotal": true
        },
        {
          "id": 31,
          "name": "基本攻撃力アップ",
          "type": "normal",
          "data": [31, 10, 2, 20, 0, 0, 0, 0, 0, 0, 28, 8, -1, 0],
          "npCost": 175,
          "isTotal": true
        },
        {
          "id": 61,
          "name": "攻撃間隔短縮",
          "type": "ultra",
          "data": [61, 10, 11, 74, 0, 0, 0, 0, 0, 0, 82, 14, -1, 1],
          "npCost": 225,
          "isTotal": true
        },
        {
          "id": 25,
          "name": "生産コスト割引",
          "type": "ultra",
          "data": [25, 10, 40, 400, 0, 0, 0, 0, 0, 0, 31, 14, -1, 1],
          "npCost": 225,
          "isTotal": true
        },
        {
          "id": 58,
          "name": "シールドブレイカー",
          "type": "ultra",
          "data": [58, 10, 16, 70, 0, 0, 0, 0, 0, 0, 78, 12, -1, 1],
          "npCost": 285,
          "isTotal": true
        }
      ]
    }
  }
}

