{
  "unitId": 386,
  "coreData": {
    "forms": [
      {
        "formId": 0,
        "name": "虹谷彩理",
        "stats": [450, 3, 10, 45, 47, 340, 350, 360, 0, 320, 0, 0, 0, 17, 6, 9, 0, 0, 0, 0, 1, 0, 0, 0, 0, 0, 0, 0, 0, 0, 0, 0, 0, 0, 0, 0, 0, 50, 200, 50, 0, 0, 0, 0, 0, 0, 0, 0, 0, 0, 0, 0, 0, 0, 0, -1, 0, -1, 0, 0, 0, 0, 0, 1, 0, 0, -1, 0, 0, 0, 0, 0, 0, 0, 0, 0],
        "animLength": 55
      },
      {
        "formId": 1,
        "name": "虹谷彩理CC",
        "stats": [450, 3, 10, 45, 47, 340, 350, 360, 0, 320, 0, 0, 0, 17, 6, 9, 0, 0, 0, 0, 1, 0, 0, 0, 0, 0, 0, 0, 0, 0, 0, 0, 0, 0, 0, 0, 0, 50, 200, 50, 0, 0, 0, 0, 0, 0, 0, 0, 0, 0, 0, 0, 0, 0, 0, -1, 0, -1, 0, 0, 0, 0, 0, 1, 0, 0, -1, 0, 0, 0, 0, 0, 0, 0, 0, 0],
        "animLength": 55
      },
      {
        "formId": 2,
        "name": "Form 3",
        "stats": [450, 3, 10, 45, 47, 340, 350, 360, 0, 320, 0, 0, 0, 17, 6, 9, 0, 0, 0, 0, 1, 0, 0, 0, 0, 0, 0, 0, 0, 0, 0, 0, 0, 0, 0, 0, 0, 50, 200, 50, 0, 0, 0, 0, 0, 0, 0, 0, 0, 0, 0, 0, 0, 0, 0, -1, 0, -1, 0, 0, 0, 0, 0, 1, 0, 0, -1, 0, 0, 0, 0, 0, 0, 0, 0, 0],
        "animLength": 30
      }
    ],
    "rarity": {
      "id": 2,
      "name": "レア",
      "maxLevels": [50, 0]
    },
    "levelRates": [20, 20, 20, 20, 20, 20, 20, 10, 10, 5, 5, 5, 5, 5, 5, 5, 5, 5, 5, 5]
  },
  "auxiliaryData": {
    "names": ["虹谷彩理", "虹谷彩理CC"],
    "talents": {
      "hasTalents": false,
      "hasUltra": false,
      "talentList": []
    }
  }
}

