{
  "unitId": 450,
  "sortKey": 5003000,
  "isLimited": false,
  "coreData": {
    "forms": [
      {
        "formId": 0,
        "name": "天城龍バベル",
        "stats": [15000, 2, 8, 5000, 124, 390, 4500, 2500, 0, 320, 1, 0, 1, 113, 0, 5, 1, 0, 0, 0, 0, 0, 0, 0, 0, 0, 0, 0, 0, 0, 0, 0, 0, 0, 0, 0, 0, 0, 0, 0, 0, 0, 0, 0, 0, 0, 0, 0, 0, 1, 1, 0, 0, 0, 0, -1, 0, -1, 0, 0, 0, 0, 0, 1, 0, 0, -1, 10, 0, 0, 0, 0, 0, 0, 0, 0, 0, 0, 0, 0, 1, 0, 0, 0, 0, 0, 0, 0, 0, 0, 0, 0, 0, 0, 0, 0, 0, 0, 0, 0, 0, 0, 0, 0, 0, 0, 0, 0, 0],
        "animLength": 211
      },
      {
        "formId": 1,
        "name": "魔城龍バベル",
        "stats": [15000, 2, 8, 5000, 124, 390, 4500, 2500, 0, 320, 1, 0, 1, 113, 0, 5, 1, 0, 0, 0, 0, 0, 0, 0, 0, 0, 0, 0, 0, 0, 0, 0, 0, 0, 0, 0, 0, 0, 0, 0, 0, 0, 0, 0, 0, 0, 0, 0, 0, 1, 1, 0, 0, 0, 0, -1, 0, -1, 0, 0, 0, 0, 0, 1, 0, 0, -1, 10, 0, 0, 0, 0, 0, 0, 0, 0, 0, 0, 0, 0, 1, 0, 0, 0, 0, 0, 0, 0, 0, 0, 0, 0, 0, 0, 0, 0, 0, 0, 0, 0, 0, 0, 0, 0, 0, 0, 0, 0, 0],
        "animLength": 211
      },
      {
        "formId": 2,
        "name": "天魔城龍バベル",
        "stats": [18000, 2, 8, 5000, 124, 390, 4500, 2500, 0, 320, 1, 0, 1, 113, 0, 5, 1, 0, 0, 0, 0, 0, 0, 0, 0, 0, 0, 0, 0, 0, 0, 0, 0, 0, 0, 0, 0, 0, 0, 0, 0, 0, 0, 0, 0, 0, 0, 0, 1, 1, 1, 0, 0, 0, 0, -1, 0, -1, 0, 0, 0, 0, 0, 1, 0, 0, -1, 10, 0, 0, 0, 0, 0, 0, 0, 0, 0, 0, 0, 0, 1, 0, 0, 0, 0, 0, 0, 0, 0, 0, 1, 0, 0, 0, 0, 0, 0, 1, 0, 0, 0, 0, 0, 0, 0, 0, 0, 0, 0],
        "animLength": 211
      }
    ],
    "rarity": {
      "id": 5,
      "name": "伝説レア",
      "maxLevels": [50, 9]
    },
    "levelRates": [20, 20, 20, 20, 20, 20, 10, 10, 5, 5, 5, 5, 5, 5, 5, 5, 5, 5, 5, 5]
  },
  "auxiliaryData": {
    "names": ["天城龍バベル", "魔城龍バベル", "天魔城龍バベル"],
    "talents": {
      "hasTalents": false,
      "hasUltra": false,
      "talentList": []
    }
  }
}

