{
  "unitId": 811,
  "sortKey": 4006100,
  "isLimited": false,
  "coreData": {
    "forms": [
      {
        "formId": 0,
        "name": "韋駄天スカンダ",
        "stats": [4000, 3, 62, 800, 0, 200, 2700, 1500, 0, 320, 1, 0, 1, 5, 0, 9, 0, 0, 0, 0, 1, 1, 0, 0, 0, 0, 0, 0, 0, 0, 0, 0, 0, 0, 0, 100, 2, 100, 90, 50, 0, 0, 0, 0, 0, 0, 0, 0, 0, 0, 0, 0, 0, 0, 0, -1, 0, -1, 0, 0, 0, 0, 0, 1, 0, 0, -1, 0, 0, 0, 0, 0, 0, 0, 0, 0, 0, 0, 0, 0, 0, 0, 0, 0, 0, 0, 0, 0, 0, 0, 0, 0, 0, 0, 0, 0, 0, 0, 0, 0, 0, 0, 0, 0, 0, 0, 0, 0, 0, 0, 812, 1, 0, 0, 0, 0, 0],
        "animLength": 301
      },
      {
        "formId": 1,
        "name": "スカンダゼタ",
        "stats": [4800, 3, 62, 1200, 0, 200, 2700, 1500, 0, 320, 1, 0, 1, 5, 0, 9, 0, 0, 0, 0, 1, 1, 0, 0, 0, 0, 0, 0, 0, 0, 0, 0, 0, 0, 0, 100, 2, 100, 120, 50, 0, 0, 0, 0, 0, 0, 0, 0, 0, 0, 0, 0, 0, 0, 0, -1, 0, -1, 0, 0, 0, 0, 0, 1, 0, 0, -1, 0, 0, 0, 0, 0, 0, 0, 0, 0, 0, 0, 0, 0, 0, 0, 0, 0, 0, 0, 0, 0, 0, 0, 0, 0, 0, 0, 0, 0, 0, 0, 0, 0, 0, 0, 0, 0, 0, 0, 0, 0, 0, 0, 812, 1, 0, 0, 0, 0, 0],
        "animLength": 301
      },
      {
        "formId": 2,
        "name": "Form 3",
        "stats": [4800, 3, 62, 1200, 0, 200, 2700, 1500, 0, 320, 1, 0, 1, 5, 0, 9, 0, 0, 0, 0, 1, 1, 0, 0, 0, 0, 0, 0, 0, 0, 0, 0, 0, 0, 0, 100, 2, 100, 120, 50, 0, 0, 0, 0, 0, 0, 0, 0, 0, 0, 0, 0, 0, 0, 0, -1, 0, -1, 0, 0, 0, 0, 0, 1, 0, 0, -1, 0, 0, 0, 0, 0, 0, 0, 0, 0, 0, 0, 0, 0, 0, 0, 0, 0, 0, 0, 0, 0, 0, 0, 0, 0, 0, 0, 0, 0, 0, 0, 0, 0, 0, 0, 0, 0, 0, 0, 0, 0, 0, 0, 812, 1, 0, 0, 0, 0, 0],
        "animLength": 30
      }
    ],
    "rarity": {
      "id": 4,
      "name": "超激レア",
      "maxLevels": [60, 70]
    },
    "levelRates": [20, 20, 20, 20, 20, 20, 10, 10, 5, 5, 5, 5, 5, 5, 5, 5, 5, 5, 5, 5]
  },
  "auxiliaryData": {
    "names": ["韋駄天スカンダ", "スカンダゼタ"],
    "talents": {
      "hasTalents": false,
      "hasUltra": false,
      "talentList": []
    }
  }
}

