{
  "eventId": 13045,
  "eventName": "海賊王商店街",
  "typeId": 13,
  "typeName": "真レジェンドストーリー",
  "prefix": "NA",
  "mapId": 45,
  "specialRule": null,
  "crownData": {
    "crownCount": 4,
    "magnifications": [100, 120, 140, 100],
    "baseDifficulty": 1
  },
  "stages": [
    {
      "stageId": 0,
      "stageName": "理容ももの毛姫",
      "baseHp": "1200000",
      "width": "5000",
      "enemyLimit": "30",
      "requiredCost": "180",
      "costLimits": {
        "lower": "0",
        "upper": "0"
      },
      "crownData": {
        "crownCount": 4,
        "magnifications": [100, 120, 140, 100],
        "baseDifficulty": 1
      },
      "treasures": [
        {
          "treasureId": "3",
          "treasureName": "ニャンピュータ",
          "probability": "1",
          "amount": "1",
          "times": "-1",
          "limitText": "-1"
        }
      ],
      "enemies": [
        {
          "enemyId": "522",
          "enemyName": "ダミー",
          "traits": [],
          "baseStats": {
            "hp": 3000,
            "ap": 1,
            "dps": 0.07,
            "speed": 0,
            "range": 2000,
            "rangeType": "範囲",
            "kbLevel": 1,
            "money": 0,
            "freq": 451,
            "foreswing": 100,
            "backswing": 31,
            "tba": 176
          },
          "stageStats": {
            "actualHp": 1200000,
            "actualAp": 400,
            "actualDps": 28.0,
            "magnification": "40000%",
            "count": "1",
            "spawnTime": "0.0s",
            "spawnTimeFrames": "0f",
            "delay": "0.1-0.1s",
            "delayFrames": "2-2f",
            "baseHpRatio": "100%",
            "isBoss": false
          },
          "abilities": {
            "immune-waves": {
              "raw_columns": 37,
              "enabled": true
            },
            "immune-knockback": {
              "raw_columns": 39,
              "enabled": true
            },
            "immune-freeze": {
              "raw_columns": 40,
              "enabled": true
            },
            "immune-slow": {
              "raw_columns": 41,
              "enabled": true
            },
            "immune-weaken": {
              "raw_columns": 42,
              "enabled": true
            },
            "curse": {
              "raw_columns": [73, 74],
              "chance": 100,
              "duration_f": 300,
              "duration_s": 10.0
            }
          }
        },
        {
          "enemyId": "146",
          "enemyName": "はぐれたヤツ",
          "traits": ["無"],
          "baseStats": {
            "hp": 500,
            "ap": 200,
            "dps": 400.0,
            "speed": 20,
            "range": 220,
            "rangeType": "範囲",
            "kbLevel": 1,
            "money": 75,
            "freq": 15,
            "foreswing": 10,
            "backswing": 5,
            "tba": 0
          },
          "stageStats": {
            "actualHp": 1500,
            "actualAp": 600,
            "actualDps": 1200.0,
            "magnification": "300%",
            "count": "0",
            "spawnTime": "4.0s",
            "spawnTimeFrames": "120f",
            "delay": "26.7-33.3s",
            "delayFrames": "800-1,000f",
            "baseHpRatio": "100%",
            "isBoss": false
          },
          "abilities": {
            "knockback": {
              "raw_columns": 20,
              "chance": 15
            }
          }
        },
        {
          "enemyId": "042",
          "enemyName": "セレブ",
          "traits": ["無"],
          "baseStats": {
            "hp": 9000,
            "ap": 5000,
            "dps": 3658.54,
            "speed": 20,
            "range": 140,
            "rangeType": "単体",
            "kbLevel": 2,
            "money": 700,
            "freq": 41,
            "foreswing": 17,
            "backswing": 24,
            "tba": 0
          },
          "stageStats": {
            "actualHp": 90000,
            "actualAp": 50000,
            "actualDps": 36585.4,
            "magnification": "1000%",
            "count": "1",
            "spawnTime": "6.7s",
            "spawnTimeFrames": "200f",
            "delay": "20.0-23.3s",
            "delayFrames": "600-700f",
            "baseHpRatio": "100%",
            "isBoss": false
          },
          "abilities": {}
        },
        {
          "enemyId": "538",
          "enemyName": "ウリボーイ",
          "traits": ["無"],
          "baseStats": {
            "hp": 55500,
            "ap": 23500,
            "dps": 26111.11,
            "speed": 20,
            "range": 130,
            "rangeType": "範囲",
            "kbLevel": 2,
            "money": 350,
            "freq": 27,
            "foreswing": 8,
            "backswing": 13,
            "tba": 10
          },
          "stageStats": {
            "actualHp": 55500,
            "actualAp": 23500,
            "actualDps": 26111.11,
            "magnification": "100%",
            "count": "1",
            "spawnTime": "20.0s",
            "spawnTimeFrames": "600f",
            "delay": "10.0-13.3s",
            "delayFrames": "300-400f",
            "baseHpRatio": "100%",
            "isBoss": false
          },
          "abilities": {
            "mini-wave": {
              "raw_columns": [27, 28, 86],
              "chance": 100,
              "level": 5
            }
          }
        },
        {
          "enemyId": "612",
          "enemyName": "ハニワンワン",
          "traits": ["古"],
          "baseStats": {
            "hp": 300000,
            "ap": 20000,
            "dps": 8333.33,
            "speed": 4,
            "range": 120,
            "rangeType": "単体",
            "kbLevel": 1,
            "money": 300,
            "freq": 72,
            "foreswing": 25,
            "backswing": 14,
            "tba": 24
          },
          "stageStats": {
            "actualHp": 300000,
            "actualAp": 20000,
            "actualDps": 8333.33,
            "magnification": "100%",
            "count": "8",
            "spawnTime": "20.0s",
            "spawnTimeFrames": "600f",
            "delay": "16.7-23.3s",
            "delayFrames": "500-700f",
            "baseHpRatio": "100%",
            "isBoss": false
          },
          "abilities": {
            "knockback": {
              "raw_columns": 20,
              "chance": 20
            },
            "freeze": {
              "raw_columns": [21, 22],
              "chance": 20,
              "duration_f": 60,
              "duration_s": 2.0
            },
            "slow": {
              "raw_columns": [23, 24],
              "chance": 20,
              "duration_f": 60,
              "duration_s": 2.0
            },
            "mini-wave": {
              "raw_columns": [27, 28, 86],
              "chance": 100,
              "level": 4
            },
            "weaken": {
              "raw_columns": [29, 30, 31],
              "chance": 20,
              "power": 60,
              "duration_f": 50,
              "duration_s": 1.67
            },
            "curse": {
              "raw_columns": [73, 74],
              "chance": 20,
              "duration_f": 60,
              "duration_s": 2.0
            }
          }
        },
        {
          "enemyId": "407",
          "enemyName": "古代わんこ",
          "traits": ["古"],
          "baseStats": {
            "hp": 75000,
            "ap": 12000,
            "dps": 8571.43,
            "speed": 20,
            "range": 120,
            "rangeType": "範囲",
            "kbLevel": 3,
            "money": 100,
            "freq": 42,
            "foreswing": 4,
            "backswing": 38,
            "tba": 15
          },
          "stageStats": {
            "actualHp": 112500,
            "actualAp": 18000,
            "actualDps": 12857.15,
            "magnification": "150%",
            "count": "15",
            "spawnTime": "40.0s",
            "spawnTimeFrames": "1,200f",
            "delay": "13.3-16.7s",
            "delayFrames": "400-500f",
            "baseHpRatio": "100%",
            "isBoss": false
          },
          "abilities": {
            "curse": {
              "raw_columns": [73, 74],
              "chance": 35,
              "duration_f": 100,
              "duration_s": 3.33
            }
          }
        },
        {
          "enemyId": "407",
          "enemyName": "古代わんこ",
          "traits": ["古"],
          "baseStats": {
            "hp": 75000,
            "ap": 12000,
            "dps": 8571.43,
            "speed": 20,
            "range": 120,
            "rangeType": "範囲",
            "kbLevel": 3,
            "money": 100,
            "freq": 42,
            "foreswing": 4,
            "backswing": 38,
            "tba": 15
          },
          "stageStats": {
            "actualHp": 112500,
            "actualAp": 18000,
            "actualDps": 12857.15,
            "magnification": "150%",
            "count": "2",
            "spawnTime": "44.7s",
            "spawnTimeFrames": "1,340f",
            "delay": "3.3-6.7s",
            "delayFrames": "100-200f",
            "baseHpRatio": "100%",
            "isBoss": false
          },
          "abilities": {
            "curse": {
              "raw_columns": [73, 74],
              "chance": 35,
              "duration_f": 100,
              "duration_s": 3.33
            }
          }
        },
        {
          "enemyId": "538",
          "enemyName": "ウリボーイ",
          "traits": ["無"],
          "baseStats": {
            "hp": 55500,
            "ap": 23500,
            "dps": 26111.11,
            "speed": 20,
            "range": 130,
            "rangeType": "範囲",
            "kbLevel": 2,
            "money": 350,
            "freq": 27,
            "foreswing": 8,
            "backswing": 13,
            "tba": 10
          },
          "stageStats": {
            "actualHp": 55500,
            "actualAp": 23500,
            "actualDps": 26111.11,
            "magnification": "100%",
            "count": "6",
            "spawnTime": "46.7s",
            "spawnTimeFrames": "1,400f",
            "delay": "20.0-23.3s",
            "delayFrames": "600-700f",
            "baseHpRatio": "100%",
            "isBoss": false
          },
          "abilities": {
            "mini-wave": {
              "raw_columns": [27, 28, 86],
              "chance": 100,
              "level": 5
            }
          }
        },
        {
          "enemyId": "538",
          "enemyName": "ウリボーイ",
          "traits": ["無"],
          "baseStats": {
            "hp": 55500,
            "ap": 23500,
            "dps": 26111.11,
            "speed": 20,
            "range": 130,
            "rangeType": "範囲",
            "kbLevel": 2,
            "money": 350,
            "freq": 27,
            "foreswing": 8,
            "backswing": 13,
            "tba": 10
          },
          "stageStats": {
            "actualHp": 55500,
            "actualAp": 23500,
            "actualDps": 26111.11,
            "magnification": "100%",
            "count": "1",
            "spawnTime": "46.7s",
            "spawnTimeFrames": "1,400f",
            "delay": "10.0-13.3s",
            "delayFrames": "300-400f",
            "baseHpRatio": "100%",
            "isBoss": true
          },
          "abilities": {
            "mini-wave": {
              "raw_columns": [27, 28, 86],
              "chance": 100,
              "level": 5
            }
          }
        },
        {
          "enemyId": "547",
          "enemyName": "マーさん",
          "traits": ["無"],
          "baseStats": {
            "hp": 1250000,
            "ap": 16000,
            "dps": 6233.77,
            "speed": 4,
            "range": 260,
            "rangeType": "範囲",
            "kbLevel": 1,
            "money": 1000,
            "freq": 77,
            "foreswing": 6,
            "backswing": 11,
            "tba": 36
          },
          "stageStats": {
            "actualHp": 1250000,
            "actualAp": 16000,
            "actualDps": 6233.77,
            "magnification": "100%",
            "count": "1",
            "spawnTime": "46.7s",
            "spawnTimeFrames": "1,400f",
            "delay": "66.7-66.7s",
            "delayFrames": "2,000-2,000f",
            "baseHpRatio": "100%",
            "isBoss": false
          },
          "abilities": {
            "mini-wave": {
              "raw_columns": [27, 28, 86],
              "chance": 100,
              "level": 3
            }
          }
        },
        {
          "enemyId": "547",
          "enemyName": "マーさん",
          "traits": ["無"],
          "baseStats": {
            "hp": 1250000,
            "ap": 16000,
            "dps": 6233.77,
            "speed": 4,
            "range": 260,
            "rangeType": "範囲",
            "kbLevel": 1,
            "money": 1000,
            "freq": 77,
            "foreswing": 6,
            "backswing": 11,
            "tba": 36
          },
          "stageStats": {
            "actualHp": 1250000,
            "actualAp": 16000,
            "actualDps": 6233.77,
            "magnification": "100%",
            "count": "1",
            "spawnTime": "60.0s",
            "spawnTimeFrames": "1,800f",
            "delay": "66.7-66.7s",
            "delayFrames": "2,000-2,000f",
            "baseHpRatio": "100%",
            "isBoss": false
          },
          "abilities": {
            "mini-wave": {
              "raw_columns": [27, 28, 86],
              "chance": 100,
              "level": 3
            }
          }
        },
        {
          "enemyId": "547",
          "enemyName": "マーさん",
          "traits": ["無"],
          "baseStats": {
            "hp": 1250000,
            "ap": 16000,
            "dps": 6233.77,
            "speed": 4,
            "range": 260,
            "rangeType": "範囲",
            "kbLevel": 1,
            "money": 1000,
            "freq": 77,
            "foreswing": 6,
            "backswing": 11,
            "tba": 36
          },
          "stageStats": {
            "actualHp": 1250000,
            "actualAp": 16000,
            "actualDps": 6233.77,
            "magnification": "100%",
            "count": "1",
            "spawnTime": "73.3s",
            "spawnTimeFrames": "2,200f",
            "delay": "66.7-66.7s",
            "delayFrames": "2,000-2,000f",
            "baseHpRatio": "100%",
            "isBoss": false
          },
          "abilities": {
            "mini-wave": {
              "raw_columns": [27, 28, 86],
              "chance": 100,
              "level": 3
            }
          }
        }
      ]
    },
    {
      "stageId": 1,
      "stageName": "スタンバイ民宿",
      "baseHp": "900000",
      "width": "3400",
      "enemyLimit": "30",
      "requiredCost": "180",
      "costLimits": {
        "lower": "0",
        "upper": "0"
      },
      "crownData": {
        "crownCount": 4,
        "magnifications": [100, 120, 140, 100],
        "baseDifficulty": 1
      },
      "treasures": [
        {
          "treasureId": "0",
          "treasureName": "スピードアップ",
          "probability": "1",
          "amount": "1",
          "times": "-1",
          "limitText": "-1"
        }
      ],
      "enemies": [
        {
          "enemyId": "315",
          "enemyName": "ダミー",
          "traits": [],
          "baseStats": {
            "hp": 1500,
            "ap": 50,
            "dps": 2.0,
            "speed": 0,
            "range": 1000,
            "rangeType": "単体",
            "kbLevel": 1,
            "money": 0,
            "freq": 751,
            "foreswing": 2,
            "backswing": 10,
            "tba": 375
          },
          "stageStats": {
            "actualHp": 900000,
            "actualAp": 30000,
            "actualDps": 1200.0,
            "magnification": "60000%",
            "count": "0",
            "spawnTime": "0.0s",
            "spawnTimeFrames": "0f",
            "delay": "2.0-6.0s",
            "delayFrames": "60-180f",
            "baseHpRatio": "100%",
            "isBoss": false
          },
          "abilities": {
            "wave": {
              "raw_columns": [27, 28],
              "chance": 100,
              "level": 20
            },
            "immune-waves": {
              "raw_columns": 37,
              "enabled": true
            },
            "immune-knockback": {
              "raw_columns": 39,
              "enabled": true
            },
            "immune-freeze": {
              "raw_columns": 40,
              "enabled": true
            },
            "immune-slow": {
              "raw_columns": 41,
              "enabled": true
            },
            "immune-weaken": {
              "raw_columns": 42,
              "enabled": true
            }
          }
        },
        {
          "enemyId": "552",
          "enemyName": "デビルワン",
          "traits": ["悪"],
          "baseStats": {
            "hp": 4500,
            "ap": 2200,
            "dps": 1783.78,
            "speed": 25,
            "range": 110,
            "rangeType": "単体",
            "kbLevel": 3,
            "money": 200,
            "freq": 37,
            "foreswing": 8,
            "backswing": 10,
            "tba": 15
          },
          "stageStats": {
            "actualHp": 27000,
            "actualAp": 13200,
            "actualDps": 10702.68,
            "magnification": "600%",
            "count": "0",
            "spawnTime": "10.0s",
            "spawnTimeFrames": "300f",
            "delay": "23.3-33.3s",
            "delayFrames": "700-1,000f",
            "baseHpRatio": "100%",
            "isBoss": false
          },
          "abilities": {
            "shield": {
              "raw_columns": 87,
              "hp": 4500
            }
          }
        },
        {
          "enemyId": "552",
          "enemyName": "デビルワン",
          "traits": ["悪"],
          "baseStats": {
            "hp": 4500,
            "ap": 2200,
            "dps": 1783.78,
            "speed": 25,
            "range": 110,
            "rangeType": "単体",
            "kbLevel": 3,
            "money": 200,
            "freq": 37,
            "foreswing": 8,
            "backswing": 10,
            "tba": 15
          },
          "stageStats": {
            "actualHp": 27000,
            "actualAp": 13200,
            "actualDps": 10702.68,
            "magnification": "600%",
            "count": "1",
            "spawnTime": "30.0s",
            "spawnTimeFrames": "900f",
            "delay": "26.7-26.7s",
            "delayFrames": "800-800f",
            "baseHpRatio": "100%",
            "isBoss": false
          },
          "abilities": {
            "shield": {
              "raw_columns": 87,
              "hp": 4500
            }
          }
        },
        {
          "enemyId": "552",
          "enemyName": "デビルワン",
          "traits": ["悪"],
          "baseStats": {
            "hp": 4500,
            "ap": 2200,
            "dps": 1783.78,
            "speed": 25,
            "range": 110,
            "rangeType": "単体",
            "kbLevel": 3,
            "money": 200,
            "freq": 37,
            "foreswing": 8,
            "backswing": 10,
            "tba": 15
          },
          "stageStats": {
            "actualHp": 27000,
            "actualAp": 13200,
            "actualDps": 10702.68,
            "magnification": "600%",
            "count": "3",
            "spawnTime": "60.0s",
            "spawnTimeFrames": "1,800f",
            "delay": "1.0-2.0s",
            "delayFrames": "30-60f",
            "baseHpRatio": "100%",
            "isBoss": false
          },
          "abilities": {
            "shield": {
              "raw_columns": 87,
              "hp": 4500
            }
          }
        },
        {
          "enemyId": "552",
          "enemyName": "デビルワン",
          "traits": ["悪"],
          "baseStats": {
            "hp": 4500,
            "ap": 2200,
            "dps": 1783.78,
            "speed": 25,
            "range": 110,
            "rangeType": "単体",
            "kbLevel": 3,
            "money": 200,
            "freq": 37,
            "foreswing": 8,
            "backswing": 10,
            "tba": 15
          },
          "stageStats": {
            "actualHp": 27000,
            "actualAp": 13200,
            "actualDps": 10702.68,
            "magnification": "600%",
            "count": "15",
            "spawnTime": "0.0s",
            "spawnTimeFrames": "0f",
            "delay": "6.7-10.0s",
            "delayFrames": "200-300f",
            "baseHpRatio": "99%",
            "isBoss": false
          },
          "abilities": {
            "shield": {
              "raw_columns": 87,
              "hp": 4500
            }
          }
        },
        {
          "enemyId": "552",
          "enemyName": "デビルワン",
          "traits": ["悪"],
          "baseStats": {
            "hp": 4500,
            "ap": 2200,
            "dps": 1783.78,
            "speed": 25,
            "range": 110,
            "rangeType": "単体",
            "kbLevel": 3,
            "money": 200,
            "freq": 37,
            "foreswing": 8,
            "backswing": 10,
            "tba": 15
          },
          "stageStats": {
            "actualHp": 27000,
            "actualAp": 13200,
            "actualDps": 10702.68,
            "magnification": "600%",
            "count": "1",
            "spawnTime": "0.0s",
            "spawnTimeFrames": "0f",
            "delay": "2.0-6.0s",
            "delayFrames": "60-180f",
            "baseHpRatio": "99%",
            "isBoss": true
          },
          "abilities": {
            "shield": {
              "raw_columns": 87,
              "hp": 4500
            }
          }
        },
        {
          "enemyId": "556",
          "enemyName": "ヘルゴリラー",
          "traits": ["悪"],
          "baseStats": {
            "hp": 85000,
            "ap": 6868,
            "dps": 12877.5,
            "speed": 18,
            "range": 160,
            "rangeType": "範囲",
            "kbLevel": 4,
            "money": 500,
            "freq": 16,
            "foreswing": 6,
            "backswing": 10,
            "tba": 0
          },
          "stageStats": {
            "actualHp": 255000,
            "actualAp": 20604,
            "actualDps": 38632.5,
            "magnification": "300%",
            "count": "5",
            "spawnTime": "0.0s",
            "spawnTimeFrames": "0f",
            "delay": "20.0-23.3s",
            "delayFrames": "600-700f",
            "baseHpRatio": "99%",
            "isBoss": false
          },
          "abilities": {
            "savage-blow": {
              "raw_columns": 75,
              "chance": 100,
              "power": 1.1
            }
          }
        },
        {
          "enemyId": "413",
          "enemyName": "コライノくん",
          "traits": ["古"],
          "baseStats": {
            "hp": 2400000,
            "ap": 12000,
            "dps": 30000.0,
            "speed": 4,
            "range": 80,
            "rangeType": "範囲",
            "kbLevel": 1,
            "money": 1000,
            "freq": 12,
            "foreswing": 6,
            "backswing": 6,
            "tba": 0
          },
          "stageStats": {
            "actualHp": 2400000,
            "actualAp": 12000,
            "actualDps": 30000.0,
            "magnification": "100%",
            "count": "2",
            "spawnTime": "0.0s",
            "spawnTimeFrames": "0f",
            "delay": "20.0-20.0s",
            "delayFrames": "600-600f",
            "baseHpRatio": "99%",
            "isBoss": false
          },
          "abilities": {
            "curse": {
              "raw_columns": [73, 74],
              "chance": 100,
              "duration_f": 300,
              "duration_s": 10.0
            }
          }
        },
        {
          "enemyId": "586",
          "enemyName": "ミッドナイトナカイ",
          "traits": ["悪"],
          "baseStats": {
            "hp": 300000,
            "ap": 23000,
            "dps": 16829.27,
            "speed": 25,
            "range": 300,
            "rangeType": "範囲",
            "kbLevel": 20,
            "money": 800,
            "freq": 41,
            "foreswing": 20,
            "backswing": 21,
            "tba": 0
          },
          "stageStats": {
            "actualHp": 300000,
            "actualAp": 23000,
            "actualDps": 16829.27,
            "magnification": "100%",
            "count": "1",
            "spawnTime": "0.0s",
            "spawnTimeFrames": "0f",
            "delay": "13.3-13.3s",
            "delayFrames": "400-400f",
            "baseHpRatio": "99%",
            "isBoss": false
          },
          "abilities": {
            "shield": {
              "raw_columns": 87,
              "hp": 80000
            }
          }
        }
      ]
    },
    {
      "stageId": 2,
      "stageName": "アベン・ジャズ喫茶",
      "baseHp": "1220000",
      "width": "4600",
      "enemyLimit": "20",
      "requiredCost": "200",
      "costLimits": {
        "lower": "0",
        "upper": "0"
      },
      "crownData": {
        "crownCount": 4,
        "magnifications": [100, 120, 140, 100],
        "baseDifficulty": 1
      },
      "treasures": [
        {
          "treasureId": "4",
          "treasureName": "おかめはちもく",
          "probability": "1",
          "amount": "1",
          "times": "-1",
          "limitText": "-1"
        }
      ],
      "enemies": [
        {
          "enemyId": "412",
          "enemyName": "イングリッス",
          "traits": ["古"],
          "baseStats": {
            "hp": 50000,
            "ap": 12500,
            "dps": 28846.15,
            "speed": 40,
            "range": 110,
            "rangeType": "単体",
            "kbLevel": 5,
            "money": 50,
            "freq": 13,
            "foreswing": 6,
            "backswing": 7,
            "tba": 0
          },
          "stageStats": {
            "actualHp": 75000,
            "actualAp": 18750,
            "actualDps": 43269.22,
            "magnification": "150%",
            "count": "8",
            "spawnTime": "13.3s",
            "spawnTimeFrames": "400f",
            "delay": "10.0-13.3s",
            "delayFrames": "300-400f",
            "baseHpRatio": "100%",
            "isBoss": false
          },
          "abilities": {
            "curse": {
              "raw_columns": [73, 74],
              "chance": 100,
              "duration_f": 150,
              "duration_s": 5.0
            }
          }
        },
        {
          "enemyId": "612",
          "enemyName": "ハニワンワン",
          "traits": ["古"],
          "baseStats": {
            "hp": 300000,
            "ap": 20000,
            "dps": 8333.33,
            "speed": 4,
            "range": 120,
            "rangeType": "単体",
            "kbLevel": 1,
            "money": 300,
            "freq": 72,
            "foreswing": 25,
            "backswing": 14,
            "tba": 24
          },
          "stageStats": {
            "actualHp": 300000,
            "actualAp": 20000,
            "actualDps": 8333.33,
            "magnification": "100%",
            "count": "2",
            "spawnTime": "16.7s",
            "spawnTimeFrames": "500f",
            "delay": "20.0-23.3s",
            "delayFrames": "600-700f",
            "baseHpRatio": "100%",
            "isBoss": false
          },
          "abilities": {
            "knockback": {
              "raw_columns": 20,
              "chance": 20
            },
            "freeze": {
              "raw_columns": [21, 22],
              "chance": 20,
              "duration_f": 60,
              "duration_s": 2.0
            },
            "slow": {
              "raw_columns": [23, 24],
              "chance": 20,
              "duration_f": 60,
              "duration_s": 2.0
            },
            "mini-wave": {
              "raw_columns": [27, 28, 86],
              "chance": 100,
              "level": 4
            },
            "weaken": {
              "raw_columns": [29, 30, 31],
              "chance": 20,
              "power": 60,
              "duration_f": 50,
              "duration_s": 1.67
            },
            "curse": {
              "raw_columns": [73, 74],
              "chance": 20,
              "duration_f": 60,
              "duration_s": 2.0
            }
          }
        },
        {
          "enemyId": "022",
          "enemyName": "ガガガガ",
          "traits": ["浮"],
          "baseStats": {
            "hp": 5000,
            "ap": 350,
            "dps": 119.32,
            "speed": 20,
            "range": 340,
            "rangeType": "範囲",
            "kbLevel": 1,
            "money": 1800,
            "freq": 88,
            "foreswing": 34,
            "backswing": 54,
            "tba": 0
          },
          "stageStats": {
            "actualHp": 200000,
            "actualAp": 14000,
            "actualDps": 4772.8,
            "magnification": "4000%",
            "count": "3",
            "spawnTime": "60.0s",
            "spawnTimeFrames": "1,800f",
            "delay": "66.7-66.7s",
            "delayFrames": "2,000-2,000f",
            "baseHpRatio": "100%",
            "isBoss": false
          },
          "abilities": {}
        },
        {
          "enemyId": "612",
          "enemyName": "ハニワンワン",
          "traits": ["古"],
          "baseStats": {
            "hp": 300000,
            "ap": 20000,
            "dps": 8333.33,
            "speed": 4,
            "range": 120,
            "rangeType": "単体",
            "kbLevel": 1,
            "money": 300,
            "freq": 72,
            "foreswing": 25,
            "backswing": 14,
            "tba": 24
          },
          "stageStats": {
            "actualHp": 300000,
            "actualAp": 20000,
            "actualDps": 8333.33,
            "magnification": "100%",
            "count": "6",
            "spawnTime": "73.3s",
            "spawnTimeFrames": "2,200f",
            "delay": "16.7-23.3s",
            "delayFrames": "500-700f",
            "baseHpRatio": "100%",
            "isBoss": false
          },
          "abilities": {
            "knockback": {
              "raw_columns": 20,
              "chance": 20
            },
            "freeze": {
              "raw_columns": [21, 22],
              "chance": 20,
              "duration_f": 60,
              "duration_s": 2.0
            },
            "slow": {
              "raw_columns": [23, 24],
              "chance": 20,
              "duration_f": 60,
              "duration_s": 2.0
            },
            "mini-wave": {
              "raw_columns": [27, 28, 86],
              "chance": 100,
              "level": 4
            },
            "weaken": {
              "raw_columns": [29, 30, 31],
              "chance": 20,
              "power": 60,
              "duration_f": 50,
              "duration_s": 1.67
            },
            "curse": {
              "raw_columns": [73, 74],
              "chance": 20,
              "duration_f": 60,
              "duration_s": 2.0
            }
          }
        },
        {
          "enemyId": "208",
          "enemyName": "よっちゃん",
          "traits": [
            "浮",
            "エ"
          ],
          "baseStats": {
            "hp": 45000,
            "ap": 1200,
            "dps": 562.5,
            "speed": 5,
            "range": 500,
            "rangeType": "範囲",
            "kbLevel": 1,
            "money": 600,
            "freq": 64,
            "foreswing": 15,
            "backswing": 41,
            "tba": 25
          },
          "stageStats": {
            "actualHp": 225000,
            "actualAp": 6000,
            "actualDps": 2812.5,
            "magnification": "500%",
            "count": "1",
            "spawnTime": "86.7s",
            "spawnTimeFrames": "2,600f",
            "delay": "23.3-26.7s",
            "delayFrames": "700-800f",
            "baseHpRatio": "100%",
            "isBoss": false
          },
          "abilities": {
            "weaken": {
              "raw_columns": [29, 30, 31],
              "chance": 50,
              "power": 150,
              "duration_f": 10,
              "duration_s": 0.33
            }
          }
        },
        {
          "enemyId": "406",
          "enemyName": "真レジェンドブンブン",
          "traits": ["古"],
          "baseStats": {
            "hp": 3000000,
            "ap": 11111,
            "dps": 20833.12,
            "speed": 13,
            "range": 200,
            "rangeType": "範囲",
            "kbLevel": 5,
            "money": 6000,
            "freq": 16,
            "foreswing": 10,
            "backswing": 6,
            "tba": 0
          },
          "stageStats": {
            "actualHp": 3000000,
            "actualAp": 11111,
            "actualDps": 20833.12,
            "magnification": "100%",
            "count": "1",
            "spawnTime": "88.0s",
            "spawnTimeFrames": "2,640f",
            "delay": "11.3-11.3s",
            "delayFrames": "340-340f",
            "baseHpRatio": "100%",
            "isBoss": false
          },
          "abilities": {
            "omni-strike": {
              "raw_columns": [35, 36],
              "standing_range": 300,
              "omni_range": [
                -300,
                300
              ]
            },
            "curse": {
              "raw_columns": [73, 74],
              "chance": 100,
              "duration_f": 300,
              "duration_s": 10.0
            }
          }
        },
        {
          "enemyId": "209",
          "enemyName": "アルパッカ",
          "traits": ["エ"],
          "baseStats": {
            "hp": 175000,
            "ap": 1750,
            "dps": 583.33,
            "speed": 6,
            "range": 550,
            "rangeType": "範囲",
            "kbLevel": 2,
            "money": 1200,
            "freq": 90,
            "foreswing": 11,
            "backswing": 36,
            "tba": 40
          },
          "stageStats": {
            "actualHp": 700000,
            "actualAp": 7000,
            "actualDps": 2333.32,
            "magnification": "400%",
            "count": "1",
            "spawnTime": "89.3s",
            "spawnTimeFrames": "2,680f",
            "delay": "10.0-10.0s",
            "delayFrames": "300-300f",
            "baseHpRatio": "100%",
            "isBoss": false
          },
          "abilities": {
            "base-destroyer": {
              "raw_columns": 26,
              "enabled": true
            },
            "strengthen": {
              "raw_columns": [32, 33],
              "trigger_hp": 1,
              "power": 900
            },
            "survive": {
              "raw_columns": 34,
              "chance": 100
            }
          }
        },
        {
          "enemyId": "412",
          "enemyName": "イングリッス",
          "traits": ["古"],
          "baseStats": {
            "hp": 50000,
            "ap": 12500,
            "dps": 28846.15,
            "speed": 40,
            "range": 110,
            "rangeType": "単体",
            "kbLevel": 5,
            "money": 50,
            "freq": 13,
            "foreswing": 6,
            "backswing": 7,
            "tba": 0
          },
          "stageStats": {
            "actualHp": 75000,
            "actualAp": 18750,
            "actualDps": 43269.22,
            "magnification": "150%",
            "count": "10",
            "spawnTime": "95.3s",
            "spawnTimeFrames": "2,860f",
            "delay": "20.0-23.3s",
            "delayFrames": "600-700f",
            "baseHpRatio": "100%",
            "isBoss": false
          },
          "abilities": {
            "curse": {
              "raw_columns": [73, 74],
              "chance": 100,
              "duration_f": 150,
              "duration_s": 5.0
            }
          }
        },
        {
          "enemyId": "412",
          "enemyName": "イングリッス",
          "traits": ["古"],
          "baseStats": {
            "hp": 50000,
            "ap": 12500,
            "dps": 28846.15,
            "speed": 40,
            "range": 110,
            "rangeType": "単体",
            "kbLevel": 5,
            "money": 50,
            "freq": 13,
            "foreswing": 6,
            "backswing": 7,
            "tba": 0
          },
          "stageStats": {
            "actualHp": 75000,
            "actualAp": 18750,
            "actualDps": 43269.22,
            "magnification": "150%",
            "count": "5 ",
            "spawnTime": "95.3s",
            "spawnTimeFrames": "2,860f",
            "delay": "0.7-1.0s",
            "delayFrames": "20-30f",
            "baseHpRatio": "75%",
            "isBoss": false
          },
          "abilities": {
            "curse": {
              "raw_columns": [73, 74],
              "chance": 100,
              "duration_f": 150,
              "duration_s": 5.0
            }
          }
        }
      ]
    },
    {
      "stageId": 3,
      "stageName": "ばたり庵",
      "baseHp": "1200000",
      "width": "4800",
      "enemyLimit": "10",
      "requiredCost": "210",
      "costLimits": {
        "lower": "0",
        "upper": "0"
      },
      "crownData": {
        "crownCount": 4,
        "magnifications": [100, 120, 140, 100],
        "baseDifficulty": 1
      },
      "treasures": [
        {
          "treasureId": "3",
          "treasureName": "ニャンピュータ",
          "probability": "1",
          "amount": "1",
          "times": "-1",
          "limitText": "-1"
        }
      ],
      "enemies": [
        {
          "enemyId": "524",
          "enemyName": "ダミー",
          "traits": [],
          "baseStats": {
            "hp": 1500,
            "ap": 120,
            "dps": 14.57,
            "speed": 0,
            "range": 2000,
            "rangeType": "単体",
            "kbLevel": 1,
            "money": 0,
            "freq": 247,
            "foreswing": 148,
            "backswing": 50,
            "tba": 50
          },
          "stageStats": {
            "actualHp": 1200000,
            "actualAp": 96000,
            "actualDps": 11656.0,
            "magnification": "80000%",
            "count": "1",
            "spawnTime": "0.1s",
            "spawnTimeFrames": "2f",
            "delay": "0.1-0.1s",
            "delayFrames": "2-2f",
            "baseHpRatio": "100%",
            "isBoss": false
          },
          "abilities": {
            "immune-waves": {
              "raw_columns": 37,
              "enabled": true
            },
            "immune-knockback": {
              "raw_columns": 39,
              "enabled": true
            },
            "immune-freeze": {
              "raw_columns": 40,
              "enabled": true
            },
            "immune-slow": {
              "raw_columns": 41,
              "enabled": true
            },
            "immune-weaken": {
              "raw_columns": 42,
              "enabled": true
            },
            "surge": {
              "raw_columns": [81, 82, 83, 84],
              "chance": 100,
              "distance_start": 150,
              "distance_end": 2000,
              "level": 3
            }
          }
        },
        {
          "enemyId": "407",
          "enemyName": "古代わんこ",
          "traits": ["古"],
          "baseStats": {
            "hp": 75000,
            "ap": 12000,
            "dps": 8571.43,
            "speed": 20,
            "range": 120,
            "rangeType": "範囲",
            "kbLevel": 3,
            "money": 100,
            "freq": 42,
            "foreswing": 4,
            "backswing": 38,
            "tba": 15
          },
          "stageStats": {
            "actualHp": 112500,
            "actualAp": 18000,
            "actualDps": 12857.15,
            "magnification": "150%",
            "count": "4",
            "spawnTime": "10.0s",
            "spawnTimeFrames": "300f",
            "delay": "20.0-23.3s",
            "delayFrames": "600-700f",
            "baseHpRatio": "100%",
            "isBoss": false
          },
          "abilities": {
            "curse": {
              "raw_columns": [73, 74],
              "chance": 35,
              "duration_f": 100,
              "duration_s": 3.33
            }
          }
        },
        {
          "enemyId": "291",
          "enemyName": "スカルボクサー",
          "traits": ["ゾ"],
          "baseStats": {
            "hp": 100000,
            "ap": 7997,
            "dps": 8272.76,
            "speed": 18,
            "range": 175,
            "rangeType": "範囲",
            "kbLevel": 2,
            "money": 900,
            "freq": 29,
            "foreswing": 1,
            "backswing": 13,
            "tba": 0
          },
          "stageStats": {
            "actualHp": 300000,
            "actualAp": 23991,
            "actualDps": 24818.28,
            "magnification": "300%",
            "count": "1",
            "spawnTime": "36.7s",
            "spawnTimeFrames": "1,100f",
            "delay": "33.3-33.3s",
            "delayFrames": "1,000-1,000f",
            "baseHpRatio": "100%",
            "isBoss": false
          },
          "abilities": {
            "multi-hit": {
              "raw_columns": [3, 55, 56],
              "hits": [6800, 400, 797],
              "timings": [1, 8, 16]
            },
            "burrow": {
              "raw_columns": [43, 44],
              "times": 1,
              "distance": 1125
            },
            "revive": {
              "raw_columns": [45, 46, 47],
              "times": 1,
              "duration_f": 240,
              "duration_s": 8.0,
              "hp_ratio": 100
            }
          }
        },
        {
          "enemyId": "407",
          "enemyName": "古代わんこ",
          "traits": ["古"],
          "baseStats": {
            "hp": 75000,
            "ap": 12000,
            "dps": 8571.43,
            "speed": 20,
            "range": 120,
            "rangeType": "範囲",
            "kbLevel": 3,
            "money": 100,
            "freq": 42,
            "foreswing": 4,
            "backswing": 38,
            "tba": 15
          },
          "stageStats": {
            "actualHp": 112500,
            "actualAp": 18000,
            "actualDps": 12857.15,
            "magnification": "150%",
            "count": "0",
            "spawnTime": "10.0s",
            "spawnTimeFrames": "300f",
            "delay": "33.3-40.0s",
            "delayFrames": "1,000-1,200f",
            "baseHpRatio": "99%",
            "isBoss": false
          },
          "abilities": {
            "curse": {
              "raw_columns": [73, 74],
              "chance": 35,
              "duration_f": 100,
              "duration_s": 3.33
            }
          }
        },
        {
          "enemyId": "407",
          "enemyName": "古代わんこ",
          "traits": ["古"],
          "baseStats": {
            "hp": 75000,
            "ap": 12000,
            "dps": 8571.43,
            "speed": 20,
            "range": 120,
            "rangeType": "範囲",
            "kbLevel": 3,
            "money": 100,
            "freq": 42,
            "foreswing": 4,
            "backswing": 38,
            "tba": 15
          },
          "stageStats": {
            "actualHp": 112500,
            "actualAp": 18000,
            "actualDps": 12857.15,
            "magnification": "150%",
            "count": "8",
            "spawnTime": "10.0s",
            "spawnTimeFrames": "300f",
            "delay": "10.0-10.0s",
            "delayFrames": "300-300f",
            "baseHpRatio": "99%",
            "isBoss": false
          },
          "abilities": {
            "curse": {
              "raw_columns": [73, 74],
              "chance": 35,
              "duration_f": 100,
              "duration_s": 3.33
            }
          }
        },
        {
          "enemyId": "291",
          "enemyName": "スカルボクサー",
          "traits": ["ゾ"],
          "baseStats": {
            "hp": 100000,
            "ap": 7997,
            "dps": 8272.76,
            "speed": 18,
            "range": 175,
            "rangeType": "範囲",
            "kbLevel": 2,
            "money": 900,
            "freq": 29,
            "foreswing": 1,
            "backswing": 13,
            "tba": 0
          },
          "stageStats": {
            "actualHp": 300000,
            "actualAp": 23991,
            "actualDps": 24818.28,
            "magnification": "300%",
            "count": "2",
            "spawnTime": "13.3s",
            "spawnTimeFrames": "400f",
            "delay": "53.3-56.7s",
            "delayFrames": "1,600-1,700f",
            "baseHpRatio": "99%",
            "isBoss": false
          },
          "abilities": {
            "multi-hit": {
              "raw_columns": [3, 55, 56],
              "hits": [6800, 400, 797],
              "timings": [1, 8, 16]
            },
            "burrow": {
              "raw_columns": [43, 44],
              "times": 1,
              "distance": 1125
            },
            "revive": {
              "raw_columns": [45, 46, 47],
              "times": 1,
              "duration_f": 240,
              "duration_s": 8.0,
              "hp_ratio": 100
            }
          }
        },
        {
          "enemyId": "600",
          "enemyName": "トロリンチョ",
          "traits": ["ゾ"],
          "baseStats": {
            "hp": 390000,
            "ap": 38000,
            "dps": 34545.45,
            "speed": 15,
            "range": 300,
            "rangeType": "単体",
            "kbLevel": 2,
            "money": 550,
            "freq": 33,
            "foreswing": 14,
            "backswing": 17,
            "tba": 10
          },
          "stageStats": {
            "actualHp": 585000,
            "actualAp": 57000,
            "actualDps": 51818.18,
            "magnification": "150%",
            "count": "3",
            "spawnTime": "108.7s",
            "spawnTimeFrames": "3,260f",
            "delay": "33.3-36.7s",
            "delayFrames": "1,000-1,100f",
            "baseHpRatio": "99%",
            "isBoss": false
          },
          "abilities": {
            "immune-waves": {
              "raw_columns": 37,
              "enabled": true
            },
            "immune-surge": {
              "raw_columns": 85,
              "enabled": true
            },
            "revive": {
              "raw_columns": [45, 46, 47],
              "times": 1,
              "duration_f": 200,
              "duration_s": 6.67,
              "hp_ratio": 50
            },
            "warp": {
              "raw_columns": [65, 66, 67],
              "chance": 15,
              "distance": 1000,
              "duration_f": 60,
              "duration_s": 2.0
            }
          }
        },
        {
          "enemyId": "609",
          "enemyName": "古兵器マンボロス",
          "traits": [
            "浮",
            "古"
          ],
          "baseStats": {
            "hp": 1800000,
            "ap": 31850,
            "dps": 3437.05,
            "speed": 3,
            "range": 650,
            "rangeType": "範囲",
            "kbLevel": 3,
            "money": 3333,
            "freq": 278,
            "foreswing": 59,
            "backswing": 42,
            "tba": 105
          },
          "stageStats": {
            "actualHp": 1800000,
            "actualAp": 31850,
            "actualDps": 3437.05,
            "magnification": "100%",
            "count": "1",
            "spawnTime": "108.0s",
            "spawnTimeFrames": "3,240f",
            "delay": "11.3-11.3s",
            "delayFrames": "340-340f",
            "baseHpRatio": "99%",
            "isBoss": true
          },
          "abilities": {
            "multi-hit": {
              "raw_columns": [3, 55, 56],
              "hits": [19600, 9800, 2450],
              "timings": [59, 64, 69]
            },
            "long-distance": {
              "raw_columns": [35, 36],
              "standing_range": 150,
              "ld_range": [150, 650]
            },
            "freeze": {
              "raw_columns": [21, 22],
              "chance": 100,
              "duration_f": 60,
              "duration_s": 2.0
            },
            "curse": {
              "raw_columns": [73, 74],
              "chance": 100,
              "duration_f": 240,
              "duration_s": 8.0
            }
          }
        }
      ]
    },
    {
      "stageId": 4,
      "stageName": "タイタ肉屋",
      "baseHp": "1080000",
      "width": "5300",
      "enemyLimit": "30",
      "requiredCost": "200",
      "costLimits": {
        "lower": "0",
        "upper": "0"
      },
      "crownData": {
        "crownCount": 4,
        "magnifications": [100, 120, 140, 100],
        "baseDifficulty": 1
      },
      "treasures": [
        {
          "treasureId": "2",
          "treasureName": "ネコボン",
          "probability": "1",
          "amount": "1",
          "times": "-1",
          "limitText": "-1"
        }
      ],
      "enemies": [
        {
          "enemyId": "554",
          "enemyName": "ケルベローズ",
          "traits": ["悪"],
          "baseStats": {
            "hp": 2500,
            "ap": 2500,
            "dps": 1442.31,
            "speed": 10,
            "range": 120,
            "rangeType": "単体",
            "kbLevel": 1,
            "money": 66,
            "freq": 52,
            "foreswing": 13,
            "backswing": 16,
            "tba": 20
          },
          "stageStats": {
            "actualHp": 15000,
            "actualAp": 15000,
            "actualDps": 8653.86,
            "magnification": "600%",
            "count": "10",
            "spawnTime": "6.7s",
            "spawnTimeFrames": "200f",
            "delay": "2.0-4.0s",
            "delayFrames": "60-120f",
            "baseHpRatio": "100%",
            "isBoss": false
          },
          "abilities": {
            "freeze": {
              "raw_columns": [21, 22],
              "chance": 30,
              "duration_f": 120,
              "duration_s": 4.0
            }
          }
        },
        {
          "enemyId": "554",
          "enemyName": "ケルベローズ",
          "traits": ["悪"],
          "baseStats": {
            "hp": 2500,
            "ap": 2500,
            "dps": 1442.31,
            "speed": 10,
            "range": 120,
            "rangeType": "単体",
            "kbLevel": 1,
            "money": 66,
            "freq": 52,
            "foreswing": 13,
            "backswing": 16,
            "tba": 20
          },
          "stageStats": {
            "actualHp": 15000,
            "actualAp": 15000,
            "actualDps": 8653.86,
            "magnification": "600%",
            "count": "20",
            "spawnTime": "13.3s",
            "spawnTimeFrames": "400f",
            "delay": "1.0-1.0s",
            "delayFrames": "30-30f",
            "baseHpRatio": "100%",
            "isBoss": false
          },
          "abilities": {
            "freeze": {
              "raw_columns": [21, 22],
              "chance": 30,
              "duration_f": 120,
              "duration_s": 4.0
            }
          }
        },
        {
          "enemyId": "407",
          "enemyName": "古代わんこ",
          "traits": ["古"],
          "baseStats": {
            "hp": 75000,
            "ap": 12000,
            "dps": 8571.43,
            "speed": 20,
            "range": 120,
            "rangeType": "範囲",
            "kbLevel": 3,
            "money": 100,
            "freq": 42,
            "foreswing": 4,
            "backswing": 38,
            "tba": 15
          },
          "stageStats": {
            "actualHp": 112500,
            "actualAp": 18000,
            "actualDps": 12857.15,
            "magnification": "150%",
            "count": "1",
            "spawnTime": "20.0s",
            "spawnTimeFrames": "600f",
            "delay": "0.1-0.1s",
            "delayFrames": "2-2f",
            "baseHpRatio": "100%",
            "isBoss": false
          },
          "abilities": {
            "curse": {
              "raw_columns": [73, 74],
              "chance": 35,
              "duration_f": 100,
              "duration_s": 3.33
            }
          }
        },
        {
          "enemyId": "552",
          "enemyName": "デビルワン",
          "traits": ["悪"],
          "baseStats": {
            "hp": 4500,
            "ap": 2200,
            "dps": 1783.78,
            "speed": 25,
            "range": 110,
            "rangeType": "単体",
            "kbLevel": 3,
            "money": 200,
            "freq": 37,
            "foreswing": 8,
            "backswing": 10,
            "tba": 15
          },
          "stageStats": {
            "actualHp": 27000,
            "actualAp": 13200,
            "actualDps": 10702.68,
            "magnification": "600%",
            "count": "5",
            "spawnTime": "23.3s",
            "spawnTimeFrames": "700f",
            "delay": "33.3-36.7s",
            "delayFrames": "1,000-1,100f",
            "baseHpRatio": "100%",
            "isBoss": false
          },
          "abilities": {
            "shield": {
              "raw_columns": 87,
              "hp": 4500
            }
          }
        },
        {
          "enemyId": "554",
          "enemyName": "ケルベローズ",
          "traits": ["悪"],
          "baseStats": {
            "hp": 2500,
            "ap": 2500,
            "dps": 1442.31,
            "speed": 10,
            "range": 120,
            "rangeType": "単体",
            "kbLevel": 1,
            "money": 66,
            "freq": 52,
            "foreswing": 13,
            "backswing": 16,
            "tba": 20
          },
          "stageStats": {
            "actualHp": 15000,
            "actualAp": 15000,
            "actualDps": 8653.86,
            "magnification": "600%",
            "count": "8",
            "spawnTime": "80.0s",
            "spawnTimeFrames": "2,400f",
            "delay": "3.3-6.7s",
            "delayFrames": "100-200f",
            "baseHpRatio": "100%",
            "isBoss": false
          },
          "abilities": {
            "freeze": {
              "raw_columns": [21, 22],
              "chance": 30,
              "duration_f": 120,
              "duration_s": 4.0
            }
          }
        },
        {
          "enemyId": "407",
          "enemyName": "古代わんこ",
          "traits": ["古"],
          "baseStats": {
            "hp": 75000,
            "ap": 12000,
            "dps": 8571.43,
            "speed": 20,
            "range": 120,
            "rangeType": "範囲",
            "kbLevel": 3,
            "money": 100,
            "freq": 42,
            "foreswing": 4,
            "backswing": 38,
            "tba": 15
          },
          "stageStats": {
            "actualHp": 112500,
            "actualAp": 18000,
            "actualDps": 12857.15,
            "magnification": "150%",
            "count": "2",
            "spawnTime": "100.0s",
            "spawnTimeFrames": "3,000f",
            "delay": "23.3-26.7s",
            "delayFrames": "700-800f",
            "baseHpRatio": "100%",
            "isBoss": false
          },
          "abilities": {
            "curse": {
              "raw_columns": [73, 74],
              "chance": 35,
              "duration_f": 100,
              "duration_s": 3.33
            }
          }
        },
        {
          "enemyId": "554",
          "enemyName": "ケルベローズ",
          "traits": ["悪"],
          "baseStats": {
            "hp": 2500,
            "ap": 2500,
            "dps": 1442.31,
            "speed": 10,
            "range": 120,
            "rangeType": "単体",
            "kbLevel": 1,
            "money": 66,
            "freq": 52,
            "foreswing": 13,
            "backswing": 16,
            "tba": 20
          },
          "stageStats": {
            "actualHp": 15000,
            "actualAp": 15000,
            "actualDps": 8653.86,
            "magnification": "600%",
            "count": "0",
            "spawnTime": "120.0s",
            "spawnTimeFrames": "3,600f",
            "delay": "13.3-20.0s",
            "delayFrames": "400-600f",
            "baseHpRatio": "100%",
            "isBoss": false
          },
          "abilities": {
            "freeze": {
              "raw_columns": [21, 22],
              "chance": 30,
              "duration_f": 120,
              "duration_s": 4.0
            }
          }
        },
        {
          "enemyId": "407",
          "enemyName": "古代わんこ",
          "traits": ["古"],
          "baseStats": {
            "hp": 75000,
            "ap": 12000,
            "dps": 8571.43,
            "speed": 20,
            "range": 120,
            "rangeType": "範囲",
            "kbLevel": 3,
            "money": 100,
            "freq": 42,
            "foreswing": 4,
            "backswing": 38,
            "tba": 15
          },
          "stageStats": {
            "actualHp": 112500,
            "actualAp": 18000,
            "actualDps": 12857.15,
            "magnification": "150%",
            "count": "3",
            "spawnTime": "133.3s",
            "spawnTimeFrames": "4,000f",
            "delay": "23.3-26.7s",
            "delayFrames": "700-800f",
            "baseHpRatio": "100%",
            "isBoss": false
          },
          "abilities": {
            "curse": {
              "raw_columns": [73, 74],
              "chance": 35,
              "duration_f": 100,
              "duration_s": 3.33
            }
          }
        },
        {
          "enemyId": "554",
          "enemyName": "ケルベローズ",
          "traits": ["悪"],
          "baseStats": {
            "hp": 2500,
            "ap": 2500,
            "dps": 1442.31,
            "speed": 10,
            "range": 120,
            "rangeType": "単体",
            "kbLevel": 1,
            "money": 66,
            "freq": 52,
            "foreswing": 13,
            "backswing": 16,
            "tba": 20
          },
          "stageStats": {
            "actualHp": 15000,
            "actualAp": 15000,
            "actualDps": 8653.86,
            "magnification": "600%",
            "count": "8",
            "spawnTime": "80.0s",
            "spawnTimeFrames": "2,400f",
            "delay": "3.3-6.7s",
            "delayFrames": "100-200f",
            "baseHpRatio": "100%",
            "isBoss": false
          },
          "abilities": {
            "freeze": {
              "raw_columns": [21, 22],
              "chance": 30,
              "duration_f": 120,
              "duration_s": 4.0
            }
          }
        },
        {
          "enemyId": "407",
          "enemyName": "古代わんこ",
          "traits": ["古"],
          "baseStats": {
            "hp": 75000,
            "ap": 12000,
            "dps": 8571.43,
            "speed": 20,
            "range": 120,
            "rangeType": "範囲",
            "kbLevel": 3,
            "money": 100,
            "freq": 42,
            "foreswing": 4,
            "backswing": 38,
            "tba": 15
          },
          "stageStats": {
            "actualHp": 112500,
            "actualAp": 18000,
            "actualDps": 12857.15,
            "magnification": "150%",
            "count": "0",
            "spawnTime": "233.3s",
            "spawnTimeFrames": "7,000f",
            "delay": "56.7-60.0s",
            "delayFrames": "1,700-1,800f",
            "baseHpRatio": "100%",
            "isBoss": false
          },
          "abilities": {
            "curse": {
              "raw_columns": [73, 74],
              "chance": 35,
              "duration_f": 100,
              "duration_s": 3.33
            }
          }
        },
        {
          "enemyId": "588",
          "enemyName": "デスコアラッキョ",
          "traits": ["悪"],
          "baseStats": {
            "hp": 1270000,
            "ap": 23500,
            "dps": 7050.0,
            "speed": 5,
            "range": 190,
            "rangeType": "範囲",
            "kbLevel": 4,
            "money": 900,
            "freq": 100,
            "foreswing": 21,
            "backswing": 9,
            "tba": 40
          },
          "stageStats": {
            "actualHp": 1270000,
            "actualAp": 23500,
            "actualDps": 7050.0,
            "magnification": "100%",
            "count": "1",
            "spawnTime": "0.1s",
            "spawnTimeFrames": "2f",
            "delay": "0.1-0.1s",
            "delayFrames": "2-2f",
            "baseHpRatio": "99%",
            "isBoss": false
          },
          "abilities": {
            "wave": {
              "raw_columns": [27, 28],
              "chance": 100,
              "level": 6
            },
            "shield": {
              "raw_columns": 87,
              "hp": 600000
            }
          }
        },
        {
          "enemyId": "414",
          "enemyName": "超町長",
          "traits": [
            "浮",
            "古"
          ],
          "baseStats": {
            "hp": 800000,
            "ap": 11111,
            "dps": 3787.84,
            "speed": 20,
            "range": 340,
            "rangeType": "範囲",
            "kbLevel": 1,
            "money": 1500,
            "freq": 88,
            "foreswing": 34,
            "backswing": 54,
            "tba": 0
          },
          "stageStats": {
            "actualHp": 800000,
            "actualAp": 11111,
            "actualDps": 3787.84,
            "magnification": "100%",
            "count": "1",
            "spawnTime": "0.1s",
            "spawnTimeFrames": "2f",
            "delay": "0.1-0.1s",
            "delayFrames": "2-2f",
            "baseHpRatio": "99%",
            "isBoss": true
          },
          "abilities": {
            "omni-strike": {
              "raw_columns": [35, 36],
              "standing_range": 440,
              "omni_range": [
                -440,
                440
              ]
            },
            "curse": {
              "raw_columns": [73, 74],
              "chance": 100,
              "duration_f": 60,
              "duration_s": 2.0
            }
          }
        },
        {
          "enemyId": "587",
          "enemyName": "デビルカツヤ",
          "traits": ["悪"],
          "baseStats": {
            "hp": 53000,
            "ap": 30000,
            "dps": 5263.16,
            "speed": 6,
            "range": 450,
            "rangeType": "範囲",
            "kbLevel": 2,
            "money": 550,
            "freq": 171,
            "foreswing": 32,
            "backswing": 21,
            "tba": 50
          },
          "stageStats": {
            "actualHp": 53000,
            "actualAp": 30000,
            "actualDps": 5263.16,
            "magnification": "100%",
            "count": "1",
            "spawnTime": "36.7s",
            "spawnTimeFrames": "1,100f",
            "delay": "0.1-0.1s",
            "delayFrames": "2-2f",
            "baseHpRatio": "99%",
            "isBoss": false
          },
          "abilities": {
            "multi-hit": {
              "raw_columns": [3, 55, 56],
              "hits": [15000, 10000, 5000],
              "timings": [32, 52, 72]
            },
            "long-distance": {
              "raw_columns": [35, 36],
              "standing_range": 650,
              "ld_range": [650, 900]
            },
            "freeze": {
              "raw_columns": [21, 22],
              "chance": 30,
              "duration_f": 60,
              "duration_s": 2.0
            },
            "shield": {
              "raw_columns": 87,
              "hp": 450000
            }
          }
        }
      ]
    },
    {
      "stageId": 5,
      "stageName": "イン・デペンデンス亭",
      "baseHp": "1200000",
      "width": "4800",
      "enemyLimit": "10",
      "requiredCost": "260",
      "costLimits": {
        "lower": "0",
        "upper": "0"
      },
      "crownData": {
        "crownCount": 4,
        "magnifications": [100, 120, 140, 100],
        "baseDifficulty": 1
      },
      "treasures": [
        {
          "treasureId": "5",
          "treasureName": "スニャイパー",
          "probability": "1",
          "amount": "1",
          "times": "-1",
          "limitText": "-1"
        }
      ],
      "enemies": [
        {
          "enemyId": "522",
          "enemyName": "ダミー",
          "traits": [],
          "baseStats": {
            "hp": 3000,
            "ap": 1,
            "dps": 0.07,
            "speed": 0,
            "range": 2000,
            "rangeType": "範囲",
            "kbLevel": 1,
            "money": 0,
            "freq": 451,
            "foreswing": 100,
            "backswing": 31,
            "tba": 176
          },
          "stageStats": {
            "actualHp": 1200000,
            "actualAp": 400,
            "actualDps": 28.0,
            "magnification": "40000%",
            "count": "3",
            "spawnTime": "0.0s",
            "spawnTimeFrames": "0f",
            "delay": "0.1-0.1s",
            "delayFrames": "2-2f",
            "baseHpRatio": "100%",
            "isBoss": false
          },
          "abilities": {
            "immune-waves": {
              "raw_columns": 37,
              "enabled": true
            },
            "immune-knockback": {
              "raw_columns": 39,
              "enabled": true
            },
            "immune-freeze": {
              "raw_columns": 40,
              "enabled": true
            },
            "immune-slow": {
              "raw_columns": 41,
              "enabled": true
            },
            "immune-weaken": {
              "raw_columns": 42,
              "enabled": true
            },
            "curse": {
              "raw_columns": [73, 74],
              "chance": 100,
              "duration_f": 300,
              "duration_s": 10.0
            }
          }
        },
        {
          "enemyId": "615",
          "enemyName": "大天使チビネル",
          "traits": ["天"],
          "baseStats": {
            "hp": 160000,
            "ap": 4500,
            "dps": 849.06,
            "speed": 7,
            "range": 350,
            "rangeType": "範囲",
            "kbLevel": 4,
            "money": 650,
            "freq": 159,
            "foreswing": 40,
            "backswing": 40,
            "tba": 60
          },
          "stageStats": {
            "actualHp": 320000,
            "actualAp": 9000,
            "actualDps": 1698.12,
            "magnification": "200%",
            "count": "1",
            "spawnTime": "10.0s",
            "spawnTimeFrames": "300f",
            "delay": "0.1-0.1s",
            "delayFrames": "2-2f",
            "baseHpRatio": "100%",
            "isBoss": false
          },
          "abilities": {
            "long-distance": {
              "raw_columns": [35, 36],
              "standing_range": 300,
              "ld_range": [300, 600]
            },
            "slow": {
              "raw_columns": [23, 24],
              "chance": 100,
              "duration_f": 90,
              "duration_s": 3.0
            },
            "weaken": {
              "raw_columns": [29, 30, 31],
              "chance": 100,
              "power": 90,
              "duration_f": 50,
              "duration_s": 1.67
            },
            "colossus": {
              "raw_columns": 94,
              "enabled": true
            }
          }
        },
        {
          "enemyId": "002",
          "enemyName": "例のヤツ",
          "traits": ["無"],
          "baseStats": {
            "hp": 200,
            "ap": 20,
            "dps": 20.0,
            "speed": 10,
            "range": 110,
            "rangeType": "単体",
            "kbLevel": 1,
            "money": 75,
            "freq": 30,
            "foreswing": 10,
            "backswing": 20,
            "tba": 10
          },
          "stageStats": {
            "actualHp": 8000,
            "actualAp": 800,
            "actualDps": 800.0,
            "magnification": "4000%",
            "count": "0",
            "spawnTime": "16.7s",
            "spawnTimeFrames": "500f",
            "delay": "6.7-10.0s",
            "delayFrames": "200-300f",
            "baseHpRatio": "100%",
            "isBoss": false
          },
          "abilities": {}
        },
        {
          "enemyId": "046",
          "enemyName": "殺意のわんこ",
          "traits": ["黒"],
          "baseStats": {
            "hp": 5000,
            "ap": 2000,
            "dps": 1463.41,
            "speed": 30,
            "range": 110,
            "rangeType": "単体",
            "kbLevel": 8,
            "money": 400,
            "freq": 41,
            "foreswing": 4,
            "backswing": 37,
            "tba": 0
          },
          "stageStats": {
            "actualHp": 60000,
            "actualAp": 24000,
            "actualDps": 17560.92,
            "magnification": "1200%",
            "count": "10",
            "spawnTime": "20.0s",
            "spawnTimeFrames": "600f",
            "delay": "20.0-23.3s",
            "delayFrames": "600-700f",
            "baseHpRatio": "100%",
            "isBoss": false
          },
          "abilities": {}
        },
        {
          "enemyId": "521",
          "enemyName": "ジョン・レオン",
          "traits": [
            "赤",
            "エ",
            "ゾ"
          ],
          "baseStats": {
            "hp": 3000000,
            "ap": 3500,
            "dps": 1693.55,
            "speed": 10,
            "range": 150,
            "rangeType": "範囲",
            "kbLevel": 2,
            "money": 1800,
            "freq": 62,
            "foreswing": 17,
            "backswing": 17,
            "tba": 23
          },
          "stageStats": {
            "actualHp": 3000000,
            "actualAp": 3500,
            "actualDps": 1693.55,
            "magnification": "100%",
            "count": "1",
            "spawnTime": "33.3s",
            "spawnTimeFrames": "1,000f",
            "delay": "0.1-0.1s",
            "delayFrames": "2-2f",
            "baseHpRatio": "100%",
            "isBoss": false
          },
          "abilities": {
            "long-distance": {
              "raw_columns": [35, 36],
              "standing_range": 400,
              "ld_range": [400, 600]
            }
          }
        },
        {
          "enemyId": "607",
          "enemyName": "オオウサ銀",
          "traits": ["赤"],
          "baseStats": {
            "hp": 65000,
            "ap": 9000,
            "dps": 6279.07,
            "speed": 22,
            "range": 150,
            "rangeType": "範囲",
            "kbLevel": 3,
            "money": 200,
            "freq": 43,
            "foreswing": 12,
            "backswing": 10,
            "tba": 15
          },
          "stageStats": {
            "actualHp": 130000,
            "actualAp": 18000,
            "actualDps": 12558.14,
            "magnification": "200%",
            "count": "5",
            "spawnTime": "43.3s",
            "spawnTimeFrames": "1,300f",
            "delay": "43.3-46.7s",
            "delayFrames": "1,300-1,400f",
            "baseHpRatio": "100%",
            "isBoss": false
          },
          "abilities": {
            "multi-hit": {
              "raw_columns": [3, 55, 56],
              "hits": [4500, 4500],
              "timings": [12, 14]
            },
            "long-distance": {
              "raw_columns": [35, 36],
              "standing_range": 1,
              "ld_range": [1, 151]
            },
            "knockback": {
              "raw_columns": 20,
              "chance": 30
            },
            "colossus": {
              "raw_columns": 94,
              "enabled": true
            }
          }
        },
        {
          "enemyId": "424",
          "enemyName": "オールドリー",
          "traits": ["古"],
          "baseStats": {
            "hp": 1360000,
            "ap": 9000,
            "dps": 15882.35,
            "speed": 32,
            "range": 310,
            "rangeType": "範囲",
            "kbLevel": 10,
            "money": 1080,
            "freq": 17,
            "foreswing": 4,
            "backswing": 13,
            "tba": 0
          },
          "stageStats": {
            "actualHp": 1360000,
            "actualAp": 9000,
            "actualDps": 15882.35,
            "magnification": "100%",
            "count": "1",
            "spawnTime": "80.0s",
            "spawnTimeFrames": "2,400f",
            "delay": "0.1-0.1s",
            "delayFrames": "2-2f",
            "baseHpRatio": "100%",
            "isBoss": false
          },
          "abilities": {
            "knockback": {
              "raw_columns": 20,
              "chance": 100
            },
            "slow": {
              "raw_columns": [23, 24],
              "chance": 100,
              "duration_f": 150,
              "duration_s": 5.0
            },
            "curse": {
              "raw_columns": [73, 74],
              "chance": 100,
              "duration_f": 150,
              "duration_s": 5.0
            }
          }
        },
        {
          "enemyId": "615",
          "enemyName": "大天使チビネル",
          "traits": ["天"],
          "baseStats": {
            "hp": 160000,
            "ap": 4500,
            "dps": 849.06,
            "speed": 7,
            "range": 350,
            "rangeType": "範囲",
            "kbLevel": 4,
            "money": 650,
            "freq": 159,
            "foreswing": 40,
            "backswing": 40,
            "tba": 60
          },
          "stageStats": {
            "actualHp": 320000,
            "actualAp": 9000,
            "actualDps": 1698.12,
            "magnification": "200%",
            "count": "2",
            "spawnTime": "93.3s",
            "spawnTimeFrames": "2,800f",
            "delay": "53.3-60.0s",
            "delayFrames": "1,600-1,800f",
            "baseHpRatio": "100%",
            "isBoss": false
          },
          "abilities": {
            "long-distance": {
              "raw_columns": [35, 36],
              "standing_range": 300,
              "ld_range": [300, 600]
            },
            "slow": {
              "raw_columns": [23, 24],
              "chance": 100,
              "duration_f": 90,
              "duration_s": 3.0
            },
            "weaken": {
              "raw_columns": [29, 30, 31],
              "chance": 100,
              "power": 90,
              "duration_f": 50,
              "duration_s": 1.67
            },
            "colossus": {
              "raw_columns": 94,
              "enabled": true
            }
          }
        },
        {
          "enemyId": "607",
          "enemyName": "オオウサ銀",
          "traits": ["赤"],
          "baseStats": {
            "hp": 65000,
            "ap": 9000,
            "dps": 6279.07,
            "speed": 22,
            "range": 150,
            "rangeType": "範囲",
            "kbLevel": 3,
            "money": 200,
            "freq": 43,
            "foreswing": 12,
            "backswing": 10,
            "tba": 15
          },
          "stageStats": {
            "actualHp": 130000,
            "actualAp": 18000,
            "actualDps": 12558.14,
            "magnification": "200%",
            "count": "5",
            "spawnTime": "43.3s",
            "spawnTimeFrames": "1,300f",
            "delay": "1.0-2.0s",
            "delayFrames": "30-60f",
            "baseHpRatio": "75%",
            "isBoss": false
          },
          "abilities": {
            "multi-hit": {
              "raw_columns": [3, 55, 56],
              "hits": [4500, 4500],
              "timings": [12, 14]
            },
            "long-distance": {
              "raw_columns": [35, 36],
              "standing_range": 1,
              "ld_range": [1, 151]
            },
            "knockback": {
              "raw_columns": 20,
              "chance": 30
            },
            "colossus": {
              "raw_columns": 94,
              "enabled": true
            }
          }
        }
      ]
    }
  ]
}
